setup.py
utarfile.py
micropython_cpython_utarfile.egg-info/PKG-INFO
micropython_cpython_utarfile.egg-info/SOURCES.txt
micropython_cpython_utarfile.egg-info/dependency_links.txt
micropython_cpython_utarfile.egg-info/requires.txt
micropython_cpython_utarfile.egg-info/top_level.txt