Metadata-Version: 1.2
Name: micropython-cpython-utarfile
Version: 0.2
Summary: MicroPython module utarfile ported to CPython
Home-page: https://github.com/pfalcon/micropython-lib
Author: Paul Sokolovsky
Author-email: micropython-lib@googlegroups.com
Maintainer: Paul Sokolovsky
Maintainer-email: micropython-lib@googlegroups.com
License: Python
Platform: UNKNOWN
